rails/__init__.py
rails/config.py
rails/exceptions.py
rails/request.py
rails/response.py
rails/router.py
rails/tools.py
rails/controllers/__init__.py
rails/models/__init__.py
rails/views/__init__.py
rails/views/base.py
rails/views/jinja.py
Rails-0.0.5.dist-info/DESCRIPTION.rst
Rails-0.0.5.dist-info/METADATA
Rails-0.0.5.dist-info/metadata.json
Rails-0.0.5.dist-info/RECORD
Rails-0.0.5.dist-info/top_level.txt
Rails-0.0.5.dist-info/WHEEL
